Workbook

Sheet Assumptions
A1: Vietnam Energy Transition — Green Finance Scenario Model Prepared by Huyen Nguyen, KCL
A2: Blue = editable inputs | Black = formulas | Shares & rates grouped side-by-side per instrument | Blended finance split: public sub-tranche + private sub-tranche
A3: Revised PDP8 Total Investment Need (USD bn between 2026 and 2030) | B3: 136 | C3: 136 | D3: 136 | J3: Source: Vietnam PDP8, MoIT
A4: INSTRUMENT ALLOCATION SHARES & INTEREST RATES BY SCENARIO
B5: ALLOCATION SHARE (%) | F5: INTEREST RATE (% p.a.)
A6: Instrument | B6: A Balanced | C6: B Market-led | D6: C Public-led | F6: A Balanced | G6: B Market-led | H6: C Public-led | J6: Rationale
A7: ODA / Bilateral concessional (JICA, KfW, AFD, etc) | B7: 0.04 | C7: 0.02 | D7: 0.08 | F7: 0.015 | G7: 0.015 | H7: 0.01 | J7: ODA pricing is bilaterally negotiated. Lower in C (1%) as larger volumes attract better terms. https://www.jica.go.jp/english/information/press/2025/20260331_11.html. Not to be confused with the concessional loans as tranches in the blended finance. At the moment, the traditional concessional loan is more popular than blended finance but blended finance has the potential to scale up.
A8: MDB concessional (ADB OCR / WB IBRD / IDA) | B8: 0.04 | C8: 0.02 | D8: 0.08 | F8: 0.01 | G8: 0.01 | H8: 0.009 | J8: Formula-based pricing (IBRD ~1%). 0.9% in C reflects scale-up benefit. Original 1.0% broadly correct.
A9: Blended finance — PUBLIC sub-tranche GCF grant / first-loss; DFI junior equity | B9: 0.01 | C9: 0.006 | D9: 0.03 | F9: 0.01 | G9: 0.01 | H9: 0.01 | J9: Convergence Report shows that Blended Finance is usually 1$ in concessional loans or public sourced loans is expected to rase 4$ in private funding. Public first-loss tranche (GCF, DFI subordinated) costs 0–1.5%. https://www.convergence.finance/resource/state-of-blended-finance-2025/view
A10: Blended finance — PRIVATE sub-tranche Credit-enhanced commercial co-investors | B10: 0.04 | C10: 0.024 | D10: 0.12 | F10: 0.06 | G10: 0.065 | H10: 0.06 | J10: Private co-investors enter at ~6–7% (below unblended ~8%) because public first-loss absorbs tail risk. Rate slightly higher in B (less public support). Blended portfolio avg ≈ (1%×50% + 6%×50%) = 3.5%.
A11: Green bonds — Sovereign / Quasi-Sovereign | B11: 0.1 | C11: 0.05 | D11: 0.175 | F11: 0.04 | G11: 0.043 | H11: 0.036 | J11: Currently VN 10Y yield (~4.36% Apr 2026 ). B = 4.3% (market pricing, no subsidy); C = 3.6% (heavy public issuance + SBV implicit support). https://www.reuters.com/world/asia-pacific/vietnam-ramps-up-bond-sales-spending-export-led-growth-faces-tariff-risks-2025-04-25/ https://www.worldgovernmentbonds.com/bond-historical-data/vietnam/10-years/
A12: Green bonds — Corporate | B12: 0.1 | C12: 0.1 | D12: 0.07 | F12: 0.065 | G12: 0.07 | H12: 0.06 | J12: https://www.worldgovernmentbonds.com/bond-historical-data/vietnam/10-years/
A13: Green credit — Commercial banks | B13: 0.67 | C13: 0.78 | D13: 0.445 | F13: 0.075 | G13: 0.08 | H13: 0.07 | J13: B = 8% (banks dominant, less pressure for banks to lower interest rates, can revise this number with the 2% subsidy programme); C = 7.0% (SBV refinancing lines, corporations have bond alternative → banks have less demand and thus rates decline). https://www.sbv.gov.vn/en/web/sbv_portal/w/developments-of-interest-rates-applied-by-credit-institutions-may-2025-
A14: Total Share (must = 100%) | B14: =SUM(B7:B13) -> 1 | C14: =SUM(C7:C13) -> 1 | D14: =SUM(D7:D13) -> 1
A15: Weighted Avg Cost of Finance (WACF) | B15: =B7*F7+B8*F8+B9*F9+B10*F10+B11*F11+B12*F12+B13*F13 -> 0.06425 | C15: =C7*G7+C8*G8+C9*G9+C10*G10+C11*G11+C12*G12+C13*G13 -> 0.07367 | D15: =D7*H7+D8*H8+D9*H9+D10*H10+D11*H11+D12*H12+D13*H13 -> 0.05067 | J15: WACF = Σ(Share × Rate) per scenario. Yellow = key output.
A16: Annual financing cost on PDP8 $136bn (USD bn) | B16: =B3*B15 -> 8.738 | C16: =B3*C15 -> 10.01912 | D16: =B3*D15 -> 6.89112
A18: HOW BLENDED FINANCE WORKS
A19: STRUCTURE | B19: Blended finance stacks two tranches: (1) PUBLIC first-loss/grant/concessional (GCF, DFIs, JETP partners) absorbs losses → allows (2) PRIVATE commercial investors to enter at reduced risk, typically at 5.5–7%.
A20: JETP CONTEXT | B20: Vietnam's JETP RMP (Nov 2022, $15.5bn) uses this structure. GCF/bilateral grants + DFI subordinated debt + commercial co-financing. Reported blended portfolio rates: 4.5–6%, consistent with this model.

Sheet WACF Breakdown
A1: Weighted Cost Breakdown — Shares × Rates by Instrument & Scenario
A2: Green = live links from Assumptions tab | Black = calculated here | Yellow = WACF totals
B3: ALLOCATION SHARE (%) | F3: INTEREST RATE (% p.a.) | J3: WEIGHTED COST = Share × Rate
A4: Instrument | B4: A Balanced | C4: B Market-led | D4: C Public-led | F4: A Balanced | G4: B Market-led | H4: C Public-led | J4: Wtd A | K4: Wtd B | L4: Wtd C | N4: % of WACF (Scenario A)
A5: ODA / Bilateral concessional (JICA, KfW, AFD) | B5: =Assumptions!B7 -> 0.04 | C5: =Assumptions!C7 -> 0.02 | D5: =Assumptions!D7 -> 0.08 | F5: =Assumptions!F7 -> 0.015 | G5: =Assumptions!G7 -> 0.015 | H5: =Assumptions!H7 -> 0.01 | J5: =Assumptions!B7*Assumptions!F7 -> 0.0006 | K5: =Assumptions!C7*Assumptions!G7 -> 0.0003 | L5: =Assumptions!D7*Assumptions!H7 -> 0.0008 | N5: =IF(Assumptions!B15=0,0,Assumptions!B7*Assumptions!F7/Assumptions!B15) -> 0.0093385214
A6: MDB concessional (ADB OCR / WB IBRD / IDA) | B6: =Assumptions!B8 -> 0.04 | C6: =Assumptions!C8 -> 0.02 | D6: =Assumptions!D8 -> 0.08 | F6: =Assumptions!F8 -> 0.01 | G6: =Assumptions!G8 -> 0.01 | H6: =Assumptions!H8 -> 0.009 | J6: =Assumptions!B8*Assumptions!F8 -> 0.0004 | K6: =Assumptions!C8*Assumptions!G8 -> 0.0002 | L6: =Assumptions!D8*Assumptions!H8 -> 0.00072 | N6: =IF(Assumptions!B15=0,0,Assumptions!B8*Assumptions!F8/Assumptions!B15) -> 0.0062256809
A7: Blended finance — PUBLIC sub-tranche GCF grant / first-loss; DFI junior equity | B7: =Assumptions!B9 -> 0.01 | C7: =Assumptions!C9 -> 0.006 | D7: =Assumptions!D9 -> 0.03 | F7: =Assumptions!F9 -> 0.01 | G7: =Assumptions!G9 -> 0.01 | H7: =Assumptions!H9 -> 0.01 | J7: =Assumptions!B9*Assumptions!F9 -> 0.0001 | K7: =Assumptions!C9*Assumptions!G9 -> 6e-05 | L7: =Assumptions!D9*Assumptions!H9 -> 0.0003 | N7: =IF(Assumptions!B15=0,0,Assumptions!B9*Assumptions!F9/Assumptions!B15) -> 0.0015564202
A8: Blended finance — PRIVATE sub-tranche Credit-enhanced commercial co-investors | B8: =Assumptions!B10 -> 0.04 | C8: =Assumptions!C10 -> 0.024 | D8: =Assumptions!D10 -> 0.12 | F8: =Assumptions!F10 -> 0.06 | G8: =Assumptions!G10 -> 0.065 | H8: =Assumptions!H10 -> 0.06 | J8: =Assumptions!B10*Assumptions!F10 -> 0.0024 | K8: =Assumptions!C10*Assumptions!G10 -> 0.00156 | L8: =Assumptions!D10*Assumptions!H10 -> 0.0072 | N8: =IF(Assumptions!B15=0,0,Assumptions!B10*Assumptions!F10/Assumptions!B15) -> 0.037354086
A9: Green bonds — Sovereign / Quasi-Sovereign | B9: =Assumptions!B11 -> 0.1 | C9: =Assumptions!C11 -> 0.05 | D9: =Assumptions!D11 -> 0.175 | F9: =Assumptions!F11 -> 0.04 | G9: =Assumptions!G11 -> 0.043 | H9: =Assumptions!H11 -> 0.036 | J9: =Assumptions!B11*Assumptions!F11 -> 0.004 | K9: =Assumptions!C11*Assumptions!G11 -> 0.00215 | L9: =Assumptions!D11*Assumptions!H11 -> 0.0063 | N9: =IF(Assumptions!B15=0,0,Assumptions!B11*Assumptions!F11/Assumptions!B15) -> 0.062256809
A10: Green bonds — Corporate (BIDV/VCB, ICMA-verified) | B10: =Assumptions!B12 -> 0.1 | C10: =Assumptions!C12 -> 0.1 | D10: =Assumptions!D12 -> 0.07 | F10: =Assumptions!F12 -> 0.065 | G10: =Assumptions!G12 -> 0.07 | H10: =Assumptions!H12 -> 0.06 | J10: =Assumptions!B12*Assumptions!F12 -> 0.0065 | K10: =Assumptions!C12*Assumptions!G12 -> 0.007 | L10: =Assumptions!D12*Assumptions!H12 -> 0.0042 | N10: =IF(Assumptions!B15=0,0,Assumptions!B12*Assumptions!F12/Assumptions!B15) -> 0.10116732
A11: Green credit — Commercial banks (SBV green credit lines) | B11: =Assumptions!B13 -> 0.67 | C11: =Assumptions!C13 -> 0.78 | D11: =Assumptions!D13 -> 0.445 | F11: =Assumptions!F13 -> 0.075 | G11: =Assumptions!G13 -> 0.08 | H11: =Assumptions!H13 -> 0.07 | J11: =Assumptions!B13*Assumptions!F13 -> 0.05025 | K11: =Assumptions!C13*Assumptions!G13 -> 0.0624 | L11: =Assumptions!D13*Assumptions!H13 -> 0.03115 | N11: =IF(Assumptions!B15=0,0,Assumptions!B13*Assumptions!F13/Assumptions!B15) -> 0.78210117
A12: WACF (Total) | B12: =Assumptions!B14 -> 1 | C12: =Assumptions!C14 -> 1 | D12: =Assumptions!D14 -> 1 | J12: =Assumptions!B15 -> 0.06425 | K12: =Assumptions!C15 -> 0.07367 | L12: =Assumptions!D15 -> 0.05067 | N12: =100% -> 1

Sheet Summary Dashboard
A1: Scenario Comparison — Summary Dashboard
A2: All values live-linked from Assumptions sheet.
A3: Metric | B3: Scenario A Balanced | C3: Scenario B Market-led | D3: Scenario C Public-led | F3: Comments
A4: WACF | B4: =Assumptions!B15 -> 0.06425 | C4: =Assumptions!C15 -> 0.07367 | D4: =Assumptions!D15 -> 0.05067
A5: Green bond share (sov + corp) | B5: =Assumptions!B11+Assumptions!B12 -> 0.2 | C5: =Assumptions!C11+Assumptions!C12 -> 0.15 | D5: =Assumptions!D11+Assumptions!D12 -> 0.245
A6: Bank credit share | B6: =Assumptions!B13 -> 0.67 | C6: =Assumptions!C13 -> 0.78 | D6: =Assumptions!D13 -> 0.445
A7: Concessional + blended share | B7: =Assumptions!B7+Assumptions!B8+Assumptions!B9+Assumptions!B10 -> 0.13 | C7: =Assumptions!C7+Assumptions!C8+Assumptions!C9+Assumptions!C10 -> 0.07 | D7: =Assumptions!D7+Assumptions!D8+Assumptions!D9+Assumptions!D10 -> 0.31
A8: Sovereign bond rate | B8: =Assumptions!F11 -> 0.04 | C8: =Assumptions!G11 -> 0.043 | D8: =Assumptions!H11 -> 0.036
A9: Bank lending rate | B9: =Assumptions!F13 -> 0.075 | C9: =Assumptions!G13 -> 0.08 | D9: =Assumptions!H13 -> 0.07
A10: Annual financing cost on $136bn (USD bn) | B10: =Assumptions!B16 -> 8.738 | C10: =Assumptions!C16 -> 10.01912 | D10: =Assumptions!D16 -> 6.89112
A11: Annual saving vs Scenario B (USD bn) | B11: =Assumptions!B16-Assumptions!C16 -> -1.28112 | C11: ="—" -> — | D11: =Assumptions!D16-Assumptions!C16 -> -3.128
